tuzi_mcp_tools/__init__.py
tuzi_mcp_tools/__main__.py
tuzi_mcp_tools/cli.py
tuzi_mcp_tools/core.py
tuzi_mcp_tools/mcp_server.py
tuzi_mcp_tools-2.1.0.dist-info/METADATA
tuzi_mcp_tools-2.1.0.dist-info/WHEEL
tuzi_mcp_tools-2.1.0.dist-info/entry_points.txt
tuzi_mcp_tools-2.1.0.dist-info/licenses/LICENSE
tuzi_mcp_tools-2.1.0.dist-info/RECORD
