Metadata-Version: 2.4
Name: tuzi-mcp-tools
Version: 2.1.0
Summary: Tuzi Image Generator - CLI and MCP tool interfaces for Tu-zi.com API
Project-URL: Homepage, https://github.com/example/tuzi-mcp-tools
Project-URL: Repository, https://github.com/example/tuzi-mcp-tools
Project-URL: Documentation, https://github.com/example/tuzi-mcp-tools/blob/main/README.md
Project-URL: Issues, https://github.com/example/tuzi-mcp-tools/issues
Author-email: Tuzi Tools <contact@example.com>
License: MIT
License-File: LICENSE
Keywords: ai,cli,image-generation,mcp,tuzi
Classifier: Development Status :: 4 - Beta
Classifier: Intended Audience :: Developers
Classifier: License :: OSI Approved :: MIT License
Classifier: Programming Language :: Python :: 3
Classifier: Programming Language :: Python :: 3.9
Classifier: Programming Language :: Python :: 3.10
Classifier: Programming Language :: Python :: 3.11
Classifier: Programming Language :: Python :: 3.12
Classifier: Topic :: Scientific/Engineering :: Artificial Intelligence
Classifier: Topic :: Software Development :: Libraries :: Python Modules
Requires-Python: >=3.11
Requires-Dist: mcp>=1.11.0
Requires-Dist: pathlib
Requires-Dist: pydantic>=2.0.0
Requires-Dist: requests>=2.31.0
Requires-Dist: rich>=13.0.0
Requires-Dist: typer>=0.12.0
